dwight_schrute.py
dwight_schrute-0.0.24.dist-info/METADATA
dwight_schrute-0.0.24.dist-info/WHEEL
dwight_schrute-0.0.24.dist-info/top_level.txt
dwight_schrute-0.0.24.dist-info/RECORD
