Metadata-Version: 2.4
Name: dwight_schrute
Version: 0.0.24
Summary: If Dwight Schrute was a Data Analysts he would have used this Library
Author: Hitesh Gulati
Classifier: Programming Language :: Python :: 3
Classifier: License :: OSI Approved :: MIT License
Classifier: Operating System :: OS Independent
Requires-Python: >=3.6
Dynamic: author
Dynamic: classifier
Dynamic: description
Dynamic: description-content-type
Dynamic: requires-python
Dynamic: summary
